{
    "status": 0,
    "desc": "success",
    "template": "",
    "params": null,
    "data": {
        "tickers": [
            {
                "marketId": "ETH-USDT",
                "price": "227.41",
                "volume": "336.5644",
                "bid": "227.2",
                "ask": "227.61",
                "low": "227.61",
                "high": "227.8",
                "updateAt": 1593597479111
            },
            {
                "marketId": "ETH-USDC",
                "price": "225.45",
                "volume": "16.5",
                "bid": "225.45",
                "ask": "225.51",
                "low": "225.51",
                "high": "226.25",
                "updateAt": 1593399836798
            },
            {
                "marketId": "ETH-DAI",
                "price": "218.29",
                "volume": "2.4109",
                "bid": "218.29",
                "ask": "220.04",
                "low": "220.04",
                "high": "218.89",
                "updateAt": 1593303304290
            },
            {
                "marketId": "WBTC-USDT",
                "price": "9166.23",
                "volume": "13.8766",
                "bid": "9166.23",
                "ask": "9329.4",
                "low": "9329.4",
                "high": "9189.92",
                "updateAt": 1593549095843
            },
            {
                "marketId": "ETH-SAI",
                "price": "145.48",
                "volume": "3.6783",
                "bid": "145.48",
                "ask": "149.41",
                "low": "149.41",
                "high": "149.35",
                "updateAt": 1575188948775
            },
            {
                "marketId": "ETH-BUSD",
                "price": "242.53",
                "volume": "0.02",
                "bid": "242.53",
                "ask": "243.78",
                "low": "243.78",
                "high": "242.53",
                "updateAt": 1591784724252
            }
        ]
    }
}